DjangoCloudflareCDN/__init__.py
DjangoCloudflareCDN/cloudflare_r2.py
django_cloudflare_cdn-1.0.0.dist-info/licenses/LICENSE
django_cloudflare_cdn-1.0.0.dist-info/METADATA
django_cloudflare_cdn-1.0.0.dist-info/WHEEL
django_cloudflare_cdn-1.0.0.dist-info/top_level.txt
django_cloudflare_cdn-1.0.0.dist-info/RECORD
