Metadata-Version: 2.4
Name: django-cloudflare-cdn
Version: 1.0.0
Summary: A Django package for serving static files via S3-compatible CDN (Cloudflare R2).
Home-page: https://github.com/Swe-HimelRana/django-cloudflare-cdn
Author: Himel
Author-email: python.package@himosoft.com.bd
License: MIT
Project-URL: Documentation, https://github.com/Swe-HimelRana/django-cloudflare-cdn/blob/main/README.md
Project-URL: Source, https://github.com/Swe-HimelRana/django-cloudflare-cdn
Project-URL: Tracker, https://github.com/Swe-HimelRana/django-cloudflare-cdn/issues
Keywords: django,cloudflare,cdn,storage,static files,s3,boto3
Classifier: Programming Language :: Python :: 3
Classifier: Programming Language :: Python :: 3.8
Classifier: Framework :: Django
Classifier: License :: OSI Approved :: MIT License
Classifier: Operating System :: OS Independent
Classifier: Programming Language :: Python :: 3.9
Classifier: Programming Language :: Python :: 3.10
License-File: LICENSE
Requires-Dist: django>=3.2
Requires-Dist: django-storages>=1.10
Requires-Dist: boto3>=1.18.0
Dynamic: author
Dynamic: author-email
Dynamic: classifier
Dynamic: description
Dynamic: description-content-type
Dynamic: home-page
Dynamic: keywords
Dynamic: license
Dynamic: license-file
Dynamic: project-url
Dynamic: requires-dist
Dynamic: summary
